digicircuit/__init__.py
digicircuit/boolean_parser.py
digicircuit/boolean_to_circuit.py
digicircuit/circuit.py
digicircuit/gate.py
digicircuit/kmap.py
digicircuit/latex_export.py
digicircuit-0.1.0.dist-info/licenses/LICENSE
digicircuit-0.1.0.dist-info/METADATA
digicircuit-0.1.0.dist-info/WHEEL
digicircuit-0.1.0.dist-info/entry_points.txt
digicircuit-0.1.0.dist-info/top_level.txt
digicircuit-0.1.0.dist-info/RECORD
